reflex_img_comparison_slider/__init__.py
reflex_img_comparison_slider/img_comparison_slider.py
reflex_img_comparison_slider-0.0.1.dist-info/METADATA
reflex_img_comparison_slider-0.0.1.dist-info/WHEEL
reflex_img_comparison_slider-0.0.1.dist-info/top_level.txt
reflex_img_comparison_slider-0.0.1.dist-info/RECORD
